setup.py
bas_dist/Binomialdistribution.py
bas_dist/Gaussiandistribution.py
bas_dist/Generaldistribution.py
bas_dist/__init__.py
bas_dist.egg-info/PKG-INFO
bas_dist.egg-info/SOURCES.txt
bas_dist.egg-info/dependency_links.txt
bas_dist.egg-info/not-zip-safe
bas_dist.egg-info/top_level.txt