Metadata-Version: 1.0
Name: bas-dist
Version: 0.1.5
Summary: Gaussian distributions
Home-page: UNKNOWN
Author: Pulak Deyashi
Author-email: pulakdeayshi@gmail.com
License: UNKNOWN
Platform: UNKNOWN
